ziffers/__init__.py
ziffers/common.py
ziffers/converters.py
ziffers/defaults.py
ziffers/generators.py
ziffers/mapper.py
ziffers/parser.py
ziffers/scale.py
ziffers/classes/__init__.py
ziffers/classes/items.py
ziffers/classes/root.py
ziffers/classes/sequences.py
ziffers/spec/__init__.py
ziffers/spec/scala.lark
ziffers/spec/ziffers.lark
ziffers-0.0.1.dist-info/LICENSE.txt
ziffers-0.0.1.dist-info/METADATA
ziffers-0.0.1.dist-info/WHEEL
ziffers-0.0.1.dist-info/top_level.txt
ziffers-0.0.1.dist-info/RECORD
