Metadata-Version: 2.1
Name: ziffers
Version: 0.0.1
Summary: Port of the Ziffers numerical notation for Python
Author-email: Raphaël Forment <raphael.forment@gmail.com>, Miika Alonen <amiika@gmail.com>
License: MIT License
Project-URL: homepage, https://github.com/Bubobubobubobubo/ziffers-python
Project-URL: documentation, https://github.com/Bubobubobubobubo/ziffers-python
Project-URL: repository, https://github.com/Bubobubobubobubo/ziffers-python
Keywords: mininotation,algorithmic music,parser
Classifier: Topic :: Artistic Software
Classifier: Programming Language :: Python :: 3
Classifier: License :: OSI Approved :: MIT License
Classifier: Operating System :: OS Independent
Requires-Python: >=3.10
License-File: LICENSE.txt
Requires-Dist: lark (>=1.1.5)
Requires-Dist: rich (>=12.6.0)
Requires-Dist: pytest (>=7.2.1)
